ibmBluepages/__init__.py
ibmBluepages/ibmBluepages.py
ibmBluepages-1.17.dist-info/DESCRIPTION.rst
ibmBluepages-1.17.dist-info/METADATA
ibmBluepages-1.17.dist-info/RECORD
ibmBluepages-1.17.dist-info/WHEEL
ibmBluepages-1.17.dist-info/metadata.json
ibmBluepages-1.17.dist-info/top_level.txt
