Metadata-Version: 2.0
Name: ibmBluepages
Version: 1.17
Summary: IBM Bluepages API
Home-page: https://github.com/ThomasIBM/ibmBluepages
Author: ThomasIBM
Author-email: guojial@cn.ibm.com
License: Apache License, Version 2.0
Keywords: Bluepages
Platform: UNKNOWN
Requires-Dist: httplib2
